[
    {
      "name": "LGA_CODE_2016",
      "mode": "",
      "type": "STRING",
      "description": null,
      "fields": []
    },
    {
      "name": "Median_age_persons",
      "mode": "",
      "type": "FLOAT64",
      "description": null,
      "fields": []
    },
    {
      "name": "Median_mortgage_repay_monthly",
      "mode": "",
      "type": "FLOAT64",
      "description": null,
      "fields": []
    },
    {
      "name": "Median_tot_prsnl_inc_weekly",
      "mode": "",
      "type": "FLOAT64",
      "description": null,
      "fields": []
    },
    {
      "name": "Median_rent_weekly",
      "mode": "",
      "type": "FLOAT64",
      "description": null,
      "fields": []
    },
    {
      "name": "Median_tot_fam_inc_weekly",
      "mode": "",
      "type": "FLOAT64",
      "description": null,
      "fields": []
    },
    {
      "name": "Average_num_psns_per_bedroom",
      "mode": "",
      "type": "FLOAT64",
      "description": null,
      "fields": []
    },
    {
      "name": "Median_tot_hhd_inc_weekly",
      "mode": "",
      "type": "FLOAT64",
      "description": null,
      "fields": []
    },
    {
      "name": "Average_household_size",
      "mode": "",
      "type": "FLOAT64",
      "description": null,
      "fields": []
    }
  ]